snapm/__init__.py
snapm/_snapm.py
snapm/command.py
snapm/progress.py
snapm/report.py
snapm/fsdiff/__init__.py
snapm/fsdiff/cache.py
snapm/fsdiff/changes.py
snapm/fsdiff/contentdiff.py
snapm/fsdiff/difftypes.py
snapm/fsdiff/engine.py
snapm/fsdiff/filetypes.py
snapm/fsdiff/fsdiffer.py
snapm/fsdiff/options.py
snapm/fsdiff/tree.py
snapm/fsdiff/treewalk.py
snapm/manager/__init__.py
snapm/manager/_boot.py
snapm/manager/_calendar.py
snapm/manager/_loader.py
snapm/manager/_manager.py
snapm/manager/_mounts.py
snapm/manager/_schedule.py
snapm/manager/_signals.py
snapm/manager/_timers.py
snapm/manager/plugins/__init__.py
snapm/manager/plugins/_plugin.py
snapm/manager/plugins/lvm2.py
snapm/manager/plugins/stratis.py
snapm/manager/plugins/stratislib/__init__.py
snapm/manager/plugins/stratislib/_connection.py
snapm/manager/plugins/stratislib/_constants.py
snapm/manager/plugins/stratislib/_data.py
snapm/manager/plugins/stratislib/_environment.py
snapm/manager/plugins/stratislib/_error_codes.py
snapm/manager/plugins/stratislib/_errors.py
snapm/manager/plugins/stratislib/_introspect.py
snapm/manager/plugins/stratislib/_stratisd_constants.py
snapm/manager/plugins/stratislib/_stratisd_version.py
snapm-0.7.0.data/scripts/snapm
snapm-0.7.0.dist-info/licenses/LICENSE
snapm-0.7.0.dist-info/METADATA
snapm-0.7.0.dist-info/WHEEL
snapm-0.7.0.dist-info/top_level.txt
snapm-0.7.0.dist-info/RECORD
