Metadata-Version: 2.4
Name: snapm
Version: 0.7.0
Summary: Snapshot Manager
Home-page: https://github.com/snapshotmanager/snapm
Author: Bryn M. Reeves
Author-email: "Bryn M. Reeves" <bmr@redhat.com>
License: Apache-2.0
Project-URL: Homepage, https://github.com/snapshotmanager/snapm
Project-URL: Issues, https://github.com/snapshotmanager/snapm/issues
Platform: Linux
Classifier: Development Status :: 4 - Beta
Classifier: Intended Audience :: Developers
Classifier: Intended Audience :: System Administrators
Classifier: Programming Language :: Python
Classifier: Programming Language :: Python :: 3
Classifier: Programming Language :: Python :: Implementation :: CPython
Requires-Python: >=3.9
License-File: LICENSE
Requires-Dist: boom-boot>=1.6.0
Requires-Dist: dbus-client-gen>=0.5
Requires-Dist: dbus-python-client-gen>=0.8
Requires-Dist: justbytes>=0.15
Requires-Dist: file-magic>=0.4.0
Requires-Dist: packaging
Requires-Dist: python-dateutil
Requires-Dist: wcwidth
Dynamic: license-file
